passist.py
passist-0.0.2.dist-info/DESCRIPTION.rst
passist-0.0.2.dist-info/WHEEL
passist-0.0.2.dist-info/RECORD
passist-0.0.2.dist-info/metadata.json
passist-0.0.2.dist-info/entry_points.txt
passist-0.0.2.dist-info/METADATA
passist-0.0.2.dist-info/top_level.txt
