Metadata-Version: 2.0
Name: passist
Version: 0.0.2
Summary: Simple password assistant
Home-page: https://github.com/atsmin/passist
Author: atsmin
Author-email: a.minami79@gmail.com
License: MIT
Keywords: password generator
Platform: UNKNOWN
Classifier: Development Status :: 3 - Alpha
Classifier: Intended Audience :: Developers
Classifier: Topic :: Software Development :: Build Tools
Classifier: License :: OSI Approved :: MIT License
Classifier: Programming Language :: Python :: 2
Classifier: Programming Language :: Python :: 2.6
Classifier: Programming Language :: Python :: 2.7
Classifier: Programming Language :: Python :: 3
Classifier: Programming Language :: Python :: 3.3
Classifier: Programming Language :: Python :: 3.4
Classifier: Programming Language :: Python :: 3.5
Requires-Dist: simple-crypt
Requires-Dist: pyperclip
Requires-Dist: passiter
Provides-Extra: dev
Provides-Extra: test
